.gitignore
LICENSE
MANIFEST.in
README.rst
VERSION
makefile
sage-train-track-users-guide.pdf
sage-train-track-users-guide.tex
setup.py
.github/workflows/test.yml
train_track/__init__.py
train_track/convex_core.py
train_track/free_group.py
train_track/free_group_automorphism.py
train_track/graph_map.py
train_track/graph_self_map.py
train_track/inverse_alphabet.py
train_track/inverse_graph.py
train_track/marked_graph.py
train_track/test_train_track.py
train_track/train_track_map.py
train_track.egg-info/PKG-INFO
train_track.egg-info/SOURCES.txt
train_track.egg-info/dependency_links.txt
train_track.egg-info/top_level.txt