Metadata-Version: 2.1
Name: train-track
Version: 0.1.6
Summary: Train-tracks for freegroup automorphisms
Home-page: https://github.com/coulbois/sage-train-track
Author: Thierry Coulbois, Dominique Benielli
Author-email: thierry.coulbois@univ-amu.fr
License: GPLv3.0
Keywords: SageMath Freegroup Automorphism Train-track
Platform: UNKNOWN
Classifier: Development Status :: 4 - Beta
Classifier: Intended Audience :: Science/Research
Classifier: Topic :: Software Development :: Build Tools
Classifier: Topic :: Scientific/Engineering :: Mathematics
Classifier: License :: OSI Approved :: GNU General Public License v3 or later (GPLv3+)
Classifier: Programming Language :: Python :: 2.7
License-File: LICENSE
